notion_automation/__init__.py
notion_automation/cli.py
notion_automation/create_database.py
notion_automation/notion_client/__init__.py
notion_automation/notion_client/api.py
notion_automation/notion_client/config.py
notion_automation/notion_client/logger.py
notion_automation/notion_client/models.py
notion_automation-1.0.3.dist-info/LICENSE.md
notion_automation-1.0.3.dist-info/METADATA
notion_automation-1.0.3.dist-info/WHEEL
notion_automation-1.0.3.dist-info/entry_points.txt
notion_automation-1.0.3.dist-info/top_level.txt
notion_automation-1.0.3.dist-info/RECORD
