Metadata-Version: 2.1
Name: notion_automation
Version: 1.0.3
Summary: Automate Notion database creation with JSON schemas
Home-page: https://github.com/atxtechbro/notion-automation
Author: Morgan Joyce
Author-email: morganj2k@gmail.com
Classifier: Programming Language :: Python :: 3
Classifier: License :: OSI Approved :: MIT License
Classifier: Operating System :: OS Independent
Requires-Python: >=3.6
License-File: LICENSE.md
Requires-Dist: requests
Requires-Dist: python-dotenv
Requires-Dist: pydantic
Requires-Dist: pytest
Requires-Dist: requests-mock
